capstone/__init__.py
capstone/arm.py
capstone/arm64.py
capstone/arm64_const.py
capstone/arm_const.py
capstone/capstone.dll
capstone/mips.py
capstone/mips_const.py
capstone/ppc.py
capstone/ppc_const.py
capstone/sparc.py
capstone/sparc_const.py
capstone/systemz.py
capstone/sysz_const.py
capstone/x86.py
capstone/x86_const.py
capstone/xcore.py
capstone/xcore_const.py
rekall_capstone-3.0.4.post2.dist-info/DESCRIPTION.rst
rekall_capstone-3.0.4.post2.dist-info/METADATA
rekall_capstone-3.0.4.post2.dist-info/RECORD
rekall_capstone-3.0.4.post2.dist-info/WHEEL
rekall_capstone-3.0.4.post2.dist-info/metadata.json
rekall_capstone-3.0.4.post2.dist-info/top_level.txt
